service_discovery/__init__.py
service_discovery/application_registration.py
service_discovery/config.py
service_discovery/decorators.py
service_discovery/discovery.py
service_discovery/models.py
service_discovery/service.py
service_discovery/service_discovery.py
service_discovery/testing/__init__.py
service_discovery/testing/base.py
service_discovery/testing/container.py
service_discovery/testing/models.py
prtc_service_discovery-0.4.0.dist-info/METADATA
prtc_service_discovery-0.4.0.dist-info/WHEEL
prtc_service_discovery-0.4.0.dist-info/RECORD
