Metadata-Version: 2.4
Name: prtc-service-discovery
Version: 0.4.0
Summary: A modern annotation-based library for registering FastAPI services with Consul service discovery
Project-URL: Homepage, https://github.com/perceptic/service-discovery-python
Project-URL: Documentation, https://github.com/perceptic/service-discovery-python/blob/main/README.md
Project-URL: Repository, https://github.com/perceptic/service-discovery-python
Project-URL: Issues, https://github.com/perceptic/service-discovery-python/issues
Author-email: Perceptic Technologies Ltd <martin@perceptic.ai>
License: Proprietary
Keywords: consul,fastapi,microservices,registration,service-discovery
Classifier: Development Status :: 4 - Beta
Classifier: Intended Audience :: Developers
Classifier: License :: Other/Proprietary License
Classifier: Programming Language :: Python :: 3
Classifier: Programming Language :: Python :: 3.10
Classifier: Programming Language :: Python :: 3.11
Classifier: Programming Language :: Python :: 3.12
Requires-Python: >=3.10
Requires-Dist: aiohttp>=3.10.0
Requires-Dist: fastapi>=0.115.0
Requires-Dist: pydantic-settings>=2.0.0
Requires-Dist: pydantic>=2.0.0
Requires-Dist: python-consul2>=0.1.5
Provides-Extra: dev
Requires-Dist: black>=24.10.0; extra == 'dev'
Requires-Dist: httpx>=0.28.0; extra == 'dev'
Requires-Dist: mypy>=1.14.0; extra == 'dev'
Requires-Dist: pre-commit>=4.0.0; extra == 'dev'
Requires-Dist: pytest-asyncio>=0.24.0; extra == 'dev'
Requires-Dist: pytest>=8.2.0; extra == 'dev'
Requires-Dist: ruff>=0.11.0; extra == 'dev'
Requires-Dist: testcontainers>=4.10.0; extra == 'dev'
Requires-Dist: uvicorn>=0.30.0; extra == 'dev'
Provides-Extra: test
Requires-Dist: httpx>=0.28.0; extra == 'test'
Requires-Dist: pytest-asyncio>=0.24.0; extra == 'test'
Requires-Dist: pytest>=8.2.0; extra == 'test'
Requires-Dist: testcontainers>=4.10.0; extra == 'test'
Provides-Extra: testing
Requires-Dist: httpx>=0.28.0; extra == 'testing'
Requires-Dist: pytest-asyncio>=0.24.0; extra == 'testing'
Requires-Dist: pytest>=8.2.0; extra == 'testing'
Requires-Dist: testcontainers>=4.10.0; extra == 'testing'
Requires-Dist: uvicorn>=0.30.0; extra == 'testing'
